mirrorlib/__init__.py
mirrorlib/mirrorlib.py
mirrorlib-0.1.0.dist-info/WHEEL
mirrorlib-0.1.0.dist-info/METADATA
mirrorlib-0.1.0.dist-info/RECORD
