Metadata-Version: 2.1
Name: mirrorlib
Version: 0.1.0
Summary: A generic specification for mirroring data
Author: wkrettek
Author-email: 50168688+wkrettek@users.noreply.github.com
Requires-Python: >=3.10,<4.0
Classifier: Programming Language :: Python :: 3
Classifier: Programming Language :: Python :: 3.10
